importfiler/__init__.py
importfiler/__main__.py
importfiler/_cli.py
importfiler/_main.py
importfiler/_runner.py
importfiler-0.0.2.dist-info/METADATA
importfiler-0.0.2.dist-info/WHEEL
importfiler-0.0.2.dist-info/entry_points.txt
importfiler-0.0.2.dist-info/top_level.txt
importfiler-0.0.2.dist-info/RECORD
