Metadata-Version: 2.1
Name: importfiler
Version: 0.0.2
Summary: Profile the import time of a module.
Author-email: Mario Corchero <mariocj89@gmail.com>
Maintainer-email: Mario Corchero <mariocj89@gmail.com>
Project-URL: Homepage, https://github.com/mariocj89/importfiler
Project-URL: Source, https://github.com/mariocj89/importfiler
Keywords: cli,development
Classifier: Development Status :: 3 - Alpha
Classifier: Topic :: Software Development :: Build Tools
Classifier: License :: OSI Approved :: MIT License
Classifier: Programming Language :: Python :: 3
Classifier: Programming Language :: Python :: 3 :: Only
Requires-Python: >=3.9
Requires-Dist: typer[all]
